synthetic_data_pipeline/__init__.py
synthetic_data_pipeline/__main__.py
synthetic_data_pipeline/main.py
synthetic_data_pipeline/agents/__init__.py
synthetic_data_pipeline/agents/base_agent.py
synthetic_data_pipeline/agents/filtration_agent.py
synthetic_data_pipeline/agents/query_parser_agent.py
synthetic_data_pipeline/agents/query_refiner_agent.py
synthetic_data_pipeline/agents/synthetic_data_generator_agent.py
synthetic_data_pipeline/agents/topic_extraction_agent.py
synthetic_data_pipeline/agents/web_scraping_agent.py
synthetic_data_pipeline/agents/web_search_agent.py
synthetic_data_pipeline/config/__init__.py
synthetic_data_pipeline/config/settings.py
synthetic_data_pipeline/models/__init__.py
synthetic_data_pipeline/models/data_schemas.py
synthetic_data_pipeline/services/__init__.py
synthetic_data_pipeline/services/chunking_service.py
synthetic_data_pipeline/services/gemini_service.py
synthetic_data_pipeline/services/scraping_service.py
synthetic_data_pipeline/services/tavily_service.py
synthetic_data_pipeline/utils/__init__.py
synthetic_data_pipeline/utils/json_handler.py
synthetic_data_pipeline/utils/pipeline_state_manager.py
synthetic_data_pipeline/workflows/__init__.py
synthetic_data_pipeline/workflows/main_workflow.py
synthetic_data_pipeline-0.1.8.dist-info/licenses/LICENSE
synthetic_data_pipeline-0.1.8.dist-info/METADATA
synthetic_data_pipeline-0.1.8.dist-info/WHEEL
synthetic_data_pipeline-0.1.8.dist-info/entry_points.txt
synthetic_data_pipeline-0.1.8.dist-info/top_level.txt
synthetic_data_pipeline-0.1.8.dist-info/RECORD
