Metadata-Version: 2.4
Name: synthetic-data-pipeline
Version: 0.1.8
Summary: AI-powered synthetic data generation pipeline with web search and topic extraction
Author-email: Omar Youssef <omarjooo595@gmail.com>
License: MIT
Project-URL: Homepage, https://github.com/Omar-YYoussef/Data_Gen_Agent
Project-URL: Repository, https://github.com/Omar-YYoussef/Data_Gen_Agent
Keywords: synthetic data,ai,data generation,nlp
Classifier: Development Status :: 3 - Alpha
Classifier: Intended Audience :: Developers
Classifier: License :: OSI Approved :: MIT License
Classifier: Programming Language :: Python :: 3
Classifier: Programming Language :: Python :: 3.8
Classifier: Programming Language :: Python :: 3.9
Classifier: Programming Language :: Python :: 3.10
Classifier: Programming Language :: Python :: 3.11
Classifier: Programming Language :: Python :: 3.12
Requires-Python: >=3.8
License-File: LICENSE
Requires-Dist: python-dotenv>=1.0.0
Requires-Dist: pydantic<3.0.0,>=2.7.4
Requires-Dist: google-generativeai>=0.3.0
Requires-Dist: langgraph>=0.2.20
Requires-Dist: langchain>=0.3.0
Requires-Dist: langchain-core>=0.3.0
Requires-Dist: langchain-community>=0.3.0
Requires-Dist: tavily-python>=0.7.0
Requires-Dist: crawl4ai>=0.7.0
Requires-Dist: requests>=2.31.0
Requires-Dist: beautifulsoup4>=4.12.3
Requires-Dist: aiohttp>=3.9.0
Requires-Dist: httpx>=0.25.0
Requires-Dist: Scrapy>=2.11.0
Requires-Dist: scraperapi-sdk>=1.5.3
Requires-Dist: langchain-scraperapi>=0.1.0
Requires-Dist: pandas>=2.2.3
Requires-Dist: numpy<3.0.0,>=1.26.0
Requires-Dist: jsonschema>=4.23.0
Requires-Dist: asyncio-throttle>=1.0.2
Requires-Dist: nest-asyncio>=1.5.0
Requires-Dist: langdetect>=1.0.9
Requires-Dist: structlog>=23.2.0
Requires-Dist: colorlog>=6.8.0
Requires-Dist: cryptography>=41.0.8
Requires-Dist: python-jose>=3.3.0
Provides-Extra: dev
Requires-Dist: pytest>=7.4.0; extra == "dev"
Requires-Dist: pytest-asyncio>=0.21.0; extra == "dev"
Requires-Dist: pytest-cov>=4.1.0; extra == "dev"
Requires-Dist: black>=23.10.0; extra == "dev"
Requires-Dist: isort>=5.12.0; extra == "dev"
Requires-Dist: mypy>=1.7.0; extra == "dev"
Provides-Extra: api
Requires-Dist: fastapi>=0.104.0; extra == "api"
Requires-Dist: uvicorn>=0.24.0; extra == "api"
Requires-Dist: python-multipart>=0.0.6; extra == "api"
Provides-Extra: ui
Requires-Dist: gradio>=4.0.0; extra == "ui"
Requires-Dist: streamlit>=1.28.0; extra == "ui"
Requires-Dist: plotly>=5.17.0; extra == "ui"
Provides-Extra: cli
Requires-Dist: click>=8.1.7; extra == "cli"
Requires-Dist: rich>=13.7.0; extra == "cli"
Requires-Dist: typer>=0.9.0; extra == "cli"
Provides-Extra: monitoring
Requires-Dist: prometheus-client>=0.19.0; extra == "monitoring"
Dynamic: license-file
